crowdsource/__init__.py
crowdsource/_version.py
crowdsource/enums.py
crowdsource/exceptions.py
crowdsource/server.py
crowdsource/assets/static/css/font-awesome.min.css
crowdsource/assets/static/css/index.css
crowdsource/assets/static/css/root.css
crowdsource/assets/static/fonts/fontawesome-webfont.woff
crowdsource/assets/static/fonts/fontawesome-webfont.woff2
crowdsource/assets/static/img/cs_cyan.png
crowdsource/assets/static/img/fb.svg
crowdsource/assets/static/img/in.svg
crowdsource/assets/static/img/logo.png
crowdsource/assets/static/img/logo_cyan.png
crowdsource/assets/static/img/tw.svg
crowdsource/assets/static/js/bundle.js
crowdsource/assets/static/js/perspective.wasm.worker.js
crowdsource/assets/static/js/perspective.wasm.worker.js.map
crowdsource/assets/static/js/psp.async.wasm
crowdsource/assets/templates/404.html
crowdsource/assets/templates/home.html
crowdsource/assets/templates/index.html
crowdsource/client/__init__.py
crowdsource/client/client.py
crowdsource/client/samples.py
crowdsource/client/samples_mixin.py
crowdsource/handlers/__init__.py
crowdsource/handlers/admin.py
crowdsource/handlers/base.py
crowdsource/handlers/competition.py
crowdsource/handlers/leaderboard.py
crowdsource/handlers/submission.py
crowdsource/handlers/user.py
crowdsource/handlers/validate.py
crowdsource/persistence/__init__.py
crowdsource/persistence/fixtures.py
crowdsource/persistence/models.py
crowdsource/tests/__init__.py
crowdsource/tests/test_all.py
crowdsource/tests/unit/__init__.py
crowdsource/tests/unit/test_competition.py
crowdsource/tests/unit/test_competition_utils.py
crowdsource/tests/unit/test_enums.py
crowdsource/tests/unit/test_exceptions.py
crowdsource/tests/unit/test_samples.py
crowdsource/tests/unit/test_server.py
crowdsource/tests/unit/test_submission.py
crowdsource/tests/unit/test_submission_utils.py
crowdsource/tests/unit/test_client/__init__.py
crowdsource/tests/unit/test_client/test_client.py
crowdsource/types/__init__.py
crowdsource/types/competition.py
crowdsource-0.1.0.dist-info/LICENSE
crowdsource-0.1.0.dist-info/METADATA
crowdsource-0.1.0.dist-info/WHEEL
crowdsource-0.1.0.dist-info/entry_points.txt
crowdsource-0.1.0.dist-info/top_level.txt
crowdsource-0.1.0.dist-info/RECORD
